[
    {
        "name": "kshana Kshanam",
        "link": "https://www.youtube.com/embed/yhEpcNQftpg?si=ywtMGdpRpaqNsjZO"
    },
    {
        "name": "Avara",
        "link": "https://www.youtube.com/embed/Q0zkOy0iTO0?si=ENPl4Eq0R0edxiRw",
        "shorts":"https://www.youtube.com/embed/IS1-8pbXFrk"
    },
    {
        "name": "Manam",
        "link": "https://www.youtube.com/embed/0cAMksLm7Rg?si=2NLzRMQW6r9PEP9q"
        
    },
    {
        "name": "Amigos",
        "link": "https://www.youtube.com/embed/YfeaSOsu5xE?si=VK_Jf72vIYCK73k"
    },
    {
        "name": "Remo",
        "link": "https://www.youtube.com/embed/bSuR_hQ16Uw?si=oSwEErs00M2mnZLh"
    },
    {
        "name": "HanuMan",
        "link": "https://www.youtube.com/embed/YyLDxAsoh8Y?si=EvdBhcF69S3wDGY5",
        "shorts": "https://www.youtube.com/embed/Hdj0C4-LM-w"
    }, 
    {
        "name": "Dj Tillu 2",
        "link": "https://www.youtube.com/embed/Ydeex3Wr970?si=iFhj4UKp6R4Cap0I"
    },
    {
        "name": "Ooru Peru Bhairavakona",
        "link": "https://www.youtube.com/embed/paOKIjpuLfw?si=1Zbr3LXT3n7DtlUg"
    },
    {
        "name": "Leader",
        "link": "https://www.youtube.com/embed/n7IHIiyhGg8?si=BfcI-qbDVJge6XNE"
    }
]